{
  "blockTags": [
    {
      "tagName": "minecraft:enderman_holdable",
      "entries": [
        121,
        118,
        128,
        245,
        130,
        124,
        29,
        186,
        119,
        185,
        126,
        120,
        136,
        11,
        131,
        236,
        195,
        9,
        127,
        28,
        190,
        191,
        10,
        123,
        125,
        129,
        132,
        122,
        30,
        8
      ]
    },
    {
      "tagName": "minecraft:banners",
      "entries": [
        434,
        425,
        437,
        424,
        439,
        414,
        415,
        418,
        410,
        409,
        432,
        427,
        438,
        420,
        430,
        411,
        417,
        435,
        429,
        412,
        433,
        423,
        413,
        416,
        421,
        408,
        431,
        428,
        436,
        426,
        419,
        422
      ]
    },
    {
      "tagName": "minecraft:flower_pots",
      "entries": [
        284,
        295,
        290,
        293,
        276,
        274,
        294,
        281,
        273,
        279,
        287,
        280,
        297,
        282,
        288,
        277,
        292,
        291,
        615,
        285,
        283,
        296,
        278,
        289,
        275,
        286
      ]
    },
    {
      "tagName": "minecraft:wooden_fences",
      "entries": [
        189,
        473,
        472,
        474,
        475,
        476
      ]
    },
    {
      "tagName": "minecraft:wooden_slabs",
      "entries": [
        444,
        448,
        446,
        447,
        449,
        445
      ]
    },
    {
      "tagName": "minecraft:portals",
      "entries": [
        194,
        254,
        491
      ]
    },
    {
      "tagName": "minecraft:small_flowers",
      "entries": [
        121,
        127,
        118,
        128,
        130,
        124,
        119,
        123,
        125,
        129,
        122,
        126,
        120
      ]
    },
    {
      "tagName": "minecraft:bamboo_plantable_on",
      "entries": [
        11,
        9,
        28,
        245,
        614,
        30,
        29,
        10,
        8,
        613
      ]
    },
    {
      "tagName": "minecraft:wooden_trapdoors",
      "entries": [
        215,
        217,
        219,
        218,
        220,
        216
      ]
    },
    {
      "tagName": "minecraft:jungle_logs",
      "entries": [
        55,
        37,
        49,
        42
      ]
    },
    {
      "tagName": "minecraft:wooden_stairs",
      "entries": [
        368,
        267,
        268,
        266,
        367,
        144
      ]
    },
    {
      "tagName": "minecraft:spruce_logs",
      "entries": [
        40,
        47,
        35,
        53
      ]
    },
    {
      "tagName": "minecraft:signs",
      "entries": [
        154,
        163,
        168,
        153,
        155,
        167,
        157,
        158,
        166,
        164,
        156,
        165
      ]
    },
    {
      "tagName": "minecraft:carpets",
      "entries": [
        391,
        394,
        392,
        385,
        397,
        383,
        387,
        384,
        388,
        389,
        396,
        390,
        398,
        386,
        393,
        395
      ]
    },
    {
      "tagName": "minecraft:wool",
      "entries": [
        110,
        114,
        105,
        109,
        102,
        112,
        115,
        116,
        103,
        113,
        101,
        106,
        104,
        108,
        107,
        111
      ]
    },
    {
      "tagName": "minecraft:wooden_buttons",
      "entries": [
        303,
        304,
        302,
        300,
        305,
        301
      ]
    },
    {
      "tagName": "minecraft:stairs",
      "entries": [
        624,
        260,
        620,
        628,
        267,
        632,
        487,
        332,
        443,
        626,
        268,
        377,
        625,
        244,
        144,
        376,
        249,
        622,
        629,
        162,
        243,
        621,
        266,
        623,
        368,
        630,
        619,
        627,
        631,
        375,
        367
      ]
    },
    {
      "tagName": "minecraft:logs",
      "entries": [
        44,
        40,
        55,
        39,
        51,
        52,
        41,
        46,
        43,
        36,
        38,
        56,
        57,
        50,
        45,
        54,
        37,
        48,
        47,
        34,
        35,
        49,
        53,
        42
      ]
    },
    {
      "tagName": "minecraft:stone_bricks",
      "entries": [
        222,
        221,
        224,
        223
      ]
    },
    {
      "tagName": "minecraft:beehives",
      "entries": [
        677,
        676
      ]
    },
    {
      "tagName": "minecraft:ice",
      "entries": [
        494,
        401,
        611,
        183
      ]
    },
    {
      "tagName": "minecraft:dragon_immune",
      "entries": [
        234,
        492,
        25,
        493,
        269,
        674,
        370,
        139,
        117,
        254,
        491,
        255,
        673,
        256
      ]
    },
    {
      "tagName": "minecraft:crops",
      "entries": [
        240,
        298,
        489,
        150,
        299,
        239
      ]
    },
    {
      "tagName": "minecraft:wall_signs",
      "entries": [
        163,
        168,
        167,
        166,
        164,
        165
      ]
    },
    {
      "tagName": "minecraft:slabs",
      "entries": [
        378,
        452,
        457,
        379,
        446,
        637,
        458,
        461,
        455,
        634,
        642,
        643,
        444,
        644,
        449,
        638,
        639,
        454,
        460,
        451,
        633,
        448,
        635,
        453,
        380,
        636,
        456,
        450,
        459,
        640,
        641,
        447,
        462,
        445,
        645
      ]
    },
    {
      "tagName": "minecraft:valid_spawn",
      "entries": [
        11,
        8
      ]
    },
    {
      "tagName": "minecraft:wooden_doors",
      "entries": [
        478,
        477,
        159,
        479,
        481,
        480
      ]
    },
    {
      "tagName": "minecraft:standing_signs",
      "entries": [
        154,
        153,
        155,
        157,
        158,
        156
      ]
    },
    {
      "tagName": "minecraft:trapdoors",
      "entries": [
        215,
        217,
        219,
        218,
        371,
        220,
        216
      ]
    },
    {
      "tagName": "minecraft:buttons",
      "entries": [
        303,
        304,
        302,
        300,
        181,
        305,
        301
      ]
    },
    {
      "tagName": "minecraft:flowers",
      "entries": [
        121,
        127,
        118,
        128,
        404,
        130,
        124,
        405,
        119,
        123,
        125,
        129,
        122,
        403,
        402,
        126,
        120
      ]
    },
    {
      "tagName": "minecraft:corals",
      "entries": [
        599,
        586,
        596,
        588,
        598,
        587,
        595,
        597,
        585,
        589
      ]
    },
    {
      "tagName": "minecraft:planks",
      "entries": [
        18,
        13,
        16,
        17,
        15,
        14
      ]
    },
    {
      "tagName": "minecraft:dark_oak_logs",
      "entries": [
        57,
        44,
        39,
        51
      ]
    },
    {
      "tagName": "minecraft:rails",
      "entries": [
        333,
        90,
        91,
        161
      ]
    },
    {
      "tagName": "minecraft:coral_plants",
      "entries": [
        586,
        588,
        587,
        585,
        589
      ]
    },
    {
      "tagName": "minecraft:leaves",
      "entries": [
        63,
        59,
        60,
        58,
        61,
        62
      ]
    },
    {
      "tagName": "minecraft:walls",
      "entries": [
        650,
        647,
        646,
        657,
        651,
        654,
        652,
        655,
        272,
        271,
        648,
        656,
        653,
        649
      ]
    },
    {
      "tagName": "minecraft:coral_blocks",
      "entries": [
        578,
        579,
        577,
        575,
        576
      ]
    },
    {
      "tagName": "minecraft:shulker_boxes",
      "entries": [
        511,
        513,
        502,
        509,
        512,
        510,
        514,
        515,
        508,
        504,
        517,
        507,
        503,
        501,
        516,
        506,
        505
      ]
    },
    {
      "tagName": "minecraft:bee_growables",
      "entries": [
        240,
        672,
        298,
        489,
        150,
        299,
        239
      ]
    },
    {
      "tagName": "minecraft:wooden_pressure_plates",
      "entries": [
        175,
        173,
        176,
        174,
        177,
        172
      ]
    },
    {
      "tagName": "minecraft:wither_immune",
      "entries": [
        370,
        117,
        492,
        25,
        254,
        493,
        491,
        269,
        674,
        255,
        673
      ]
    },
    {
      "tagName": "minecraft:acacia_logs",
      "entries": [
        56,
        50,
        43,
        38
      ]
    },
    {
      "tagName": "minecraft:anvil",
      "entries": [
        319,
        320,
        318
      ]
    },
    {
      "tagName": "minecraft:tall_flowers",
      "entries": [
        404,
        403,
        402,
        405
      ]
    },
    {
      "tagName": "minecraft:birch_logs",
      "entries": [
        54,
        48,
        41,
        36
      ]
    },
    {
      "tagName": "minecraft:wall_corals",
      "entries": [
        607,
        609,
        608,
        605,
        606
      ]
    },
    {
      "tagName": "minecraft:underwater_bonemeals",
      "entries": [
        97,
        607,
        586,
        596,
        608,
        587,
        597,
        605,
        599,
        609,
        588,
        598,
        595,
        585,
        606,
        589
      ]
    },
    {
      "tagName": "minecraft:impermeable",
      "entries": [
        202,
        200,
        208,
        213,
        205,
        212,
        211,
        207,
        210,
        203,
        214,
        209,
        66,
        206,
        201,
        204,
        199
      ]
    },
    {
      "tagName": "minecraft:sand",
      "entries": [
        28,
        29
      ]
    },
    {
      "tagName": "minecraft:fences",
      "entries": [
        189,
        473,
        472,
        474,
        475,
        248,
        476
      ]
    },
    {
      "tagName": "minecraft:saplings",
      "entries": [
        20,
        19,
        24,
        21,
        22,
        23
      ]
    },
    {
      "tagName": "minecraft:beds",
      "entries": [
        89,
        85,
        77,
        79,
        78,
        82,
        86,
        83,
        76,
        80,
        84,
        74,
        88,
        87,
        81,
        75
      ]
    },
    {
      "tagName": "minecraft:oak_logs",
      "entries": [
        45,
        52,
        46,
        34
      ]
    },
    {
      "tagName": "minecraft:doors",
      "entries": [
        478,
        477,
        159,
        479,
        481,
        480,
        171
      ]
    }
  ],
  "itemTags": [
    {
      "tagName": "minecraft:banners",
      "entries": [
        815,
        807,
        809,
        813,
        816,
        808,
        810,
        811,
        806,
        804,
        814,
        817,
        802,
        803,
        812,
        805
      ]
    },
    {
      "tagName": "minecraft:trapdoors",
      "entries": [
        195,
        193,
        198,
        194,
        197,
        298,
        196
      ]
    },
    {
      "tagName": "minecraft:wooden_fences",
      "entries": [
        182,
        183,
        185,
        181,
        186,
        184
      ]
    },
    {
      "tagName": "minecraft:flowers",
      "entries": [
        103,
        98,
        108,
        110,
        102,
        109,
        107,
        101,
        106,
        104,
        323,
        100,
        325,
        105,
        326,
        99,
        324
      ]
    },
    {
      "tagName": "minecraft:buttons",
      "entries": [
        174,
        260,
        264,
        262,
        261,
        259,
        263
      ]
    },
    {
      "tagName": "minecraft:wooden_slabs",
      "entries": [
        116,
        120,
        115,
        117,
        118,
        119
      ]
    },
    {
      "tagName": "minecraft:planks",
      "entries": [
        17,
        15,
        13,
        16,
        18,
        14
      ]
    },
    {
      "tagName": "minecraft:boats",
      "entries": [
        831,
        834,
        602,
        832,
        835,
        833
      ]
    },
    {
      "tagName": "minecraft:small_flowers",
      "entries": [
        103,
        98,
        108,
        110,
        102,
        109,
        107,
        101,
        106,
        104,
        100,
        105,
        99
      ]
    },
    {
      "tagName": "minecraft:dark_oak_logs",
      "entries": [
        49,
        43,
        55,
        37
      ]
    },
    {
      "tagName": "minecraft:rails",
      "entries": [
        162,
        73,
        72,
        279
      ]
    },
    {
      "tagName": "minecraft:wooden_trapdoors",
      "entries": [
        195,
        193,
        198,
        194,
        197,
        196
      ]
    },
    {
      "tagName": "minecraft:leaves",
      "entries": [
        61,
        56,
        60,
        59,
        57,
        58
      ]
    },
    {
      "tagName": "minecraft:walls",
      "entries": [
        249,
        257,
        252,
        245,
        251,
        256,
        250,
        247,
        253,
        255,
        254,
        246,
        248,
        258
      ]
    },
    {
      "tagName": "minecraft:coals",
      "entries": [
        528,
        527
      ]
    },
    {
      "tagName": "minecraft:jungle_logs",
      "entries": [
        53,
        47,
        41,
        35
      ]
    },
    {
      "tagName": "minecraft:lectern_books",
      "entries": [
        759,
        758
      ]
    },
    {
      "tagName": "minecraft:wooden_stairs",
      "entries": [
        320,
        154,
        240,
        241,
        242,
        319
      ]
    },
    {
      "tagName": "minecraft:spruce_logs",
      "entries": [
        33,
        45,
        51,
        39
      ]
    },
    {
      "tagName": "minecraft:signs",
      "entries": [
        593,
        590,
        594,
        592,
        589,
        591
      ]
    },
    {
      "tagName": "minecraft:wooden_pressure_plates",
      "entries": [
        168,
        167,
        171,
        169,
        170,
        166
      ]
    },
    {
      "tagName": "minecraft:carpets",
      "entries": [
        303,
        313,
        301,
        312,
        310,
        314,
        308,
        309,
        304,
        302,
        306,
        305,
        311,
        300,
        315,
        307
      ]
    },
    {
      "tagName": "minecraft:wool",
      "entries": [
        90,
        92,
        97,
        95,
        96,
        85,
        86,
        93,
        88,
        94,
        82,
        91,
        87,
        89,
        84,
        83
      ]
    },
    {
      "tagName": "minecraft:wooden_buttons",
      "entries": [
        260,
        264,
        262,
        261,
        259,
        263
      ]
    },
    {
      "tagName": "minecraft:acacia_logs",
      "entries": [
        54,
        36,
        48,
        42
      ]
    },
    {
      "tagName": "minecraft:stairs",
      "entries": [
        487,
        485,
        365,
        278,
        483,
        366,
        371,
        479,
        484,
        235,
        478,
        241,
        482,
        152,
        320,
        364,
        240,
        486,
        242,
        228,
        481,
        489,
        163,
        223,
        154,
        491,
        480,
        488,
        222,
        319,
        490
      ]
    },
    {
      "tagName": "minecraft:music_discs",
      "entries": [
        843,
        847,
        848,
        845,
        851,
        841,
        852,
        844,
        849,
        850,
        842,
        846
      ]
    },
    {
      "tagName": "minecraft:fishes",
      "entries": [
        625,
        629,
        626,
        630,
        628,
        627
      ]
    },
    {
      "tagName": "minecraft:anvil",
      "entries": [
        265,
        267,
        266
      ]
    },
    {
      "tagName": "minecraft:tall_flowers",
      "entries": [
        323,
        325,
        326,
        324
      ]
    },
    {
      "tagName": "minecraft:birch_logs",
      "entries": [
        34,
        46,
        40,
        52
      ]
    },
    {
      "tagName": "minecraft:logs",
      "entries": [
        49,
        53,
        33,
        45,
        54,
        51,
        55,
        50,
        52,
        37,
        36,
        41,
        48,
        35,
        47,
        43,
        34,
        46,
        40,
        39,
        32,
        44,
        38,
        42
      ]
    },
    {
      "tagName": "minecraft:stone_bricks",
      "entries": [
        206,
        208,
        207,
        205
      ]
    },
    {
      "tagName": "minecraft:arrows",
      "entries": [
        827,
        826,
        526
      ]
    },
    {
      "tagName": "minecraft:sand",
      "entries": [
        26,
        27
      ]
    },
    {
      "tagName": "minecraft:slabs",
      "entries": [
        130,
        493,
        127,
        129,
        131,
        494,
        501,
        120,
        116,
        115,
        498,
        128,
        133,
        132,
        118,
        503,
        122,
        123,
        500,
        502,
        499,
        125,
        126,
        496,
        495,
        504,
        121,
        117,
        134,
        136,
        124,
        497,
        135,
        492,
        119
      ]
    },
    {
      "tagName": "minecraft:fences",
      "entries": [
        182,
        183,
        227,
        185,
        181,
        186,
        184
      ]
    },
    {
      "tagName": "minecraft:wooden_doors",
      "entries": [
        509,
        508,
        510,
        512,
        507,
        511
      ]
    },
    {
      "tagName": "minecraft:saplings",
      "entries": [
        22,
        21,
        19,
        23,
        20,
        24
      ]
    },
    {
      "tagName": "minecraft:beds",
      "entries": [
        667,
        658,
        657,
        669,
        660,
        655,
        665,
        663,
        654,
        662,
        668,
        656,
        661,
        659,
        664,
        666
      ]
    },
    {
      "tagName": "minecraft:oak_logs",
      "entries": [
        32,
        50,
        44,
        38
      ]
    },
    {
      "tagName": "minecraft:doors",
      "entries": [
        509,
        508,
        510,
        512,
        506,
        507,
        511
      ]
    }
  ],
  "fluidTags": [
    {
      "tagName": "minecraft:lava",
      "entries": [
        4,
        3
      ]
    },
    {
      "tagName": "minecraft:water",
      "entries": [
        1,
        2
      ]
    }
  ],
  "entityTags": [
    {
      "tagName": "minecraft:beehive_inhabitors",
      "entries": [
        4
      ]
    },
    {
      "tagName": "minecraft:skeletons",
      "entries": [
        75,
        66,
        92
      ]
    },
    {
      "tagName": "minecraft:raiders",
      "entries": [
        87,
        34,
        23,
        90,
        88,
        99
      ]
    },
    {
      "tagName": "minecraft:arrows",
      "entries": [
        2,
        72
      ]
    }
  ]
}