{
  "reset": false,
  "advancementMapping": [
    {
      "key": "minecraft:recipes/decorations/campfire",
      "value": {
        "parentId": "minecraft:recipes/root",
        "criteria": [
          {
            "key": "has_coal"
          },
          {
            "key": "has_stick"
          },
          {
            "key": "has_the_recipe"
          }
        ],
        "requirements": [
          [
            "has_stick",
            "has_coal",
            "has_the_recipe"
          ]
        ]
      }
    },
    {
      "key": "minecraft:recipes/misc/coal",
      "value": {
        "parentId": "minecraft:recipes/root",
        "criteria": [
          {
            "key": "has_the_recipe"
          },
          {
            "key": "has_at_least_9_coal"
          },
          {
            "key": "has_coal_block"
          }
        ],
        "requirements": [
          [
            "has_at_least_9_coal",
            "has_coal_block",
            "has_the_recipe"
          ]
        ]
      }
    },
    {
      "key": "minecraft:recipes/building_blocks/coal_block",
      "value": {
        "parentId": "minecraft:recipes/root",
        "criteria": [
          {
            "key": "has_the_recipe"
          },
          {
            "key": "has_at_least_9_coal"
          }
        ],
        "requirements": [
          [
            "has_at_least_9_coal",
            "has_the_recipe"
          ]
        ]
      }
    },
    {
      "key": "minecraft:recipes/misc/green_dye",
      "value": {
        "parentId": "minecraft:recipes/root",
        "criteria": [
          {
            "key": "has_cactus"
          },
          {
            "key": "has_the_recipe"
          }
        ],
        "requirements": [
          [
            "has_cactus",
            "has_the_recipe"
          ]
        ]
      }
    },
    {
      "key": "minecraft:recipes/root",
      "value": {
        "criteria": [
          {
            "key": "impossible"
          }
        ],
        "requirements": [
          [
            "impossible"
          ]
        ]
      }
    }
  ],
  "identifiers": [],
  "progressMapping": [
    {
      "key": "minecraft:recipes/decorations/campfire",
      "value": [
        {
          "criterionIdentifier": "has_coal",
          "criterionProgress": [
            396,
            -1215797299
          ]
        },
        {
          "criterionIdentifier": "has_stick"
        },
        {
          "criterionIdentifier": "has_the_recipe"
        }
      ]
    },
    {
      "key": "minecraft:recipes/building_blocks/coal_block",
      "value": [
        {
          "criterionIdentifier": "has_the_recipe"
        },
        {
          "criterionIdentifier": "has_at_least_9_coal",
          "criterionProgress": [
            396,
            -1215797294
          ]
        }
      ]
    },
    {
      "key": "minecraft:recipes/misc/green_dye",
      "value": [
        {
          "criterionIdentifier": "has_cactus",
          "criterionProgress": [
            396,
            -1215797290
          ]
        },
        {
          "criterionIdentifier": "has_the_recipe"
        }
      ]
    },
    {
      "key": "minecraft:recipes/misc/coal",
      "value": [
        {
          "criterionIdentifier": "has_the_recipe"
        },
        {
          "criterionIdentifier": "has_at_least_9_coal",
          "criterionProgress": [
            396,
            -1215797295
          ]
        },
        {
          "criterionIdentifier": "has_coal_block"
        }
      ]
    },
    {
      "key": "minecraft:recipes/root",
      "value": [
        {
          "criterionIdentifier": "impossible"
        }
      ]
    }
  ]
}